{
    "srcUrlPattern": "/${owner}/${repo}-src/blob/18.2/HTMLSamples/map/json-binding.html",
    "embed": [
        {
            "label": "JS",
            "path": "18.2/JA/map/json-binding/fiddle/demo.js"
        },
        {
            "label": "HTML",
            "path": "18.2/JA/map/json-binding/fiddle/demo.html"
        },
        {
            "label": "CSS",
            "path": "18.2/JA/map/json-binding/fiddle/demo.css"
        },
        {
            "type": "htmlpage",
            "label": "サンプル",
            "url": "https://igniteui.github.io/help-samples/18.2/JA/map/json-binding/index.html"
        }
    ]
}