{
    "srcUrlPattern": "/${owner}/${repo}-src/blob/17.1/HTMLSamples/grid/multi-column-headers.html",
    "embed": [
        {
            "label": "JS",
            "path": "17.1/JA/grid/multi-column-headers/fiddle/demo.js"
        },
        {
            "label": "HTML",
            "path": "17.1/JA/grid/multi-column-headers/fiddle/demo.html"
        },
        {
            "type": "htmlpage",
            "label": "サンプル",
            "url": "https://igniteui.github.io/help-samples/17.1/JA/grid/multi-column-headers/index.html"
        }
    ]
}