{
    "srcUrlPattern": "/${owner}/${repo}-src/blob/17.2/HTMLSamples/radial-gauge/api-usage.html",
    "embed": [
        {
            "label": "JS",
            "path": "17.2/EN/radial-gauge/api-usage/fiddle/demo.js"
        },
        {
            "label": "HTML",
            "path": "17.2/EN/radial-gauge/api-usage/fiddle/demo.html"
        },
        {
            "label": "CSS",
            "path": "17.2/EN/radial-gauge/api-usage/fiddle/demo.css"
        },
        {
            "type": "htmlpage",
            "label": "Result",
            "url": "https://igniteui.github.io/help-samples/17.2/EN/radial-gauge/api-usage/index.html"
        }
    ]
}