{
    "srcUrlPattern": "/${owner}/${repo}-src/blob/22.2/HTMLSamples/editors/date-picker.html",
    "embed": [
        {
            "label": "JS",
            "path": "22.2/JA/editors/date-picker/fiddle/demo.js"
        },
        {
            "label": "HTML",
            "path": "22.2/JA/editors/date-picker/fiddle/demo.html"
        },
        {
            "label": "CSS",
            "path": "22.2/JA/editors/date-picker/fiddle/demo.css"
        },
        {
            "type": "htmlpage",
            "label": "サンプル",
            "url": "https://igniteui.github.io/help-samples/22.2/JA/editors/date-picker/index.html"
        }
    ]
}